solarmask/ARDataSet.py
solarmask/__init__.py
solarmask/active_region.py
solarmask/active_region_derived_fields.py
solarmask/active_region_parameters.py
solarmask/active_region_segments.py
solarmask/data.py
solarmask/utils.py
solarmask-1.0.5.dist-info/LICENSE
solarmask-1.0.5.dist-info/METADATA
solarmask-1.0.5.dist-info/WHEEL
solarmask-1.0.5.dist-info/top_level.txt
solarmask-1.0.5.dist-info/RECORD
