Metadata-Version: 2.1
Name: solarmask
Version: 1.0.5
Summary: An active region segmentation library
Home-page: https://github.com/SWxTREC/solarmask
Author: Theo Lincke
Author-email: thli2739@colorado.edu
Project-URL: BugTracker, https://github.com/SWxTREC/solarmask/issues
Classifier: Programming Language :: Python :: 3
Classifier: License :: OSI Approved :: MIT License
Classifier: Operating System :: OS Independent
Requires-Python: >=3.6
License-File: LICENSE
Requires-Dist: numpy
Requires-Dist: matplotlib
Requires-Dist: pandas
Requires-Dist: torch
Requires-Dist: scikit-learn
Requires-Dist: scikit-image
Requires-Dist: scipy
Requires-Dist: astropy
